encbmp
